Rdio-0.3.0.data/scripts/rdio-call
Rdio-0.3.0.dist-info/DESCRIPTION.rst
Rdio-0.3.0.dist-info/METADATA
Rdio-0.3.0.dist-info/metadata.json
Rdio-0.3.0.dist-info/RECORD
Rdio-0.3.0.dist-info/top_level.txt
Rdio-0.3.0.dist-info/WHEEL
rdioapi/__init__.py
