Metadata-Version: 2.0
Name: Rdio
Version: 0.3.0
Summary: A Python wrapper library for the Rdio web services API
Home-page: http://www.rdio.com/developers/
Author: Rdio
Author-email: developersupport@rd.io
License: MIT
Platform: any
Classifier: License :: OSI Approved :: MIT License
Classifier: Programming Language :: Python :: 2.7
Requires-Dist: oauth2
